collatz.sv
module collatz( input logic         clk,   // Clock
		input logic 	    go,    // Load value from n; start iterating
		input logic  [31:0] n,     // Start value; only read when go = 1
		output logic [31:0] dout,  // Iteration value: true after go = 1
		output logic 	    done); // True when dout reaches 1

   /* Replace this comment and the code below with your solution */
   always_ff @(posedge clk) begin
      if (go) dout <= n;
      else if (done == 1) dout <= 32'd1;
      else if (dout[0] == 0) dout <= dout >> 1;
      else dout <= (dout << 1) + dout + 1;
   end
   assign done = (dout == 32'd1) ? 1 : 0;
endmodule

range.sv
module range
   #(parameter
     RAM_WORDS = 16,            // Number of counts to store in RAM
     RAM_ADDR_BITS = 4)         // Number of RAM address bits
   (input logic         clk,    // Clock
    input logic 	go,     // Read start and start testing
    input logic [31:0] 	start,  // Number to start from or count to read
    output logic 	done,   // True once memory is filled
    output logic [15:0] count); // Iteration count once finished

   logic 		cgo;    // "go" for the Collatz iterator
   logic                cdone;  // "done" from the Collatz iterator
   logic [31:0] 	n;      // number to start the Collatz iterator

// verilator lint_off PINCONNECTEMPTY
   
   // Instantiate the Collatz iterator
   collatz c1(.clk(clk),
	      .go(cgo),
	      .n(n),
	      .done(cdone),
	      .dout());

   logic [RAM_ADDR_BITS - 1:0] 	 num;         // The iteration we are currently on
   logic [RAM_ADDR_BITS - 1:0] 	 addrSet;         // The RAM address to write too
   logic 			 running = 0; // True during the iterations

   /* Replace this comment and the code below with your solution,
      which should generate running, done, cgo, n, num, we, and din */
   
   always_ff @(posedge clk) begin
      if (go) begin
         running <= 1;
         done <= 0;
         count <= 0;
         we <= 0;
         num <= 4'h0;
         cgo <= 1;
         n <= start;
      end
      else if (running == 1) begin
         running <= 1;
         cgo <= 0;
         we <= 0;
         if (cdone == 1 && cgo != 1) begin
            if (num == 4'hf) begin
               done <= 1;
               running <= 0;
            end
            else begin
               n <= 1 + start + {28'b0, num};
               cgo <= 1;
               addrSet <= num;
               num <= num + 1;
               din <= count;
               count <= 0;
               we <= 1;
            end
         end
         else begin
            count <= count + 1;
         end
      end
      else begin
         done <= 0;
      end
      
   end


   /* Replace this comment and the code above with your solution */

   logic 			 we;                    // Write din to addr
   logic [15:0] 		 din;                   // Data to write
   logic [15:0] 		 mem[RAM_WORDS - 1:0];  // The RAM itself
   logic [RAM_ADDR_BITS - 1:0] 	 addr;                  // Address to read/write

   assign addr = we ? addrSet : start[RAM_ADDR_BITS-1:0];
   
   always_ff @(posedge clk) begin
      if (we) mem[addr] <= din;
      count <= mem[addr];      
   end

endmodule

range.vcd
$version Generated by VerilatedVcd $end
$date Tue Feb 11 18:57:16 2025
 $end
$timescale   1ps $end

 $scope module TOP $end
  $var wire  1 < clk $end
  $var wire 16 @ count [15:0] $end
  $var wire  1 ? done $end
  $var wire  1 = go $end
  $var wire 32 > start [31:0] $end
  $scope module range $end
   $var wire 32 C RAM_ADDR_BITS [31:0] $end
   $var wire 32 B RAM_WORDS [31:0] $end
   $var wire  4 A addr [3:0] $end
   $var wire  4 ' addrSet [3:0] $end
   $var wire  1 $ cdone $end
   $var wire  1 # cgo $end
   $var wire  1 < clk $end
   $var wire 16 @ count [15:0] $end
   $var wire 16 * din [15:0] $end
   $var wire  1 ? done $end
   $var wire  1 = go $end
   $var wire 16 + mem(0) [15:0] $end
   $var wire 16 , mem(1) [15:0] $end
   $var wire 16 5 mem(10) [15:0] $end
   $var wire 16 6 mem(11) [15:0] $end
   $var wire 16 7 mem(12) [15:0] $end
   $var wire 16 8 mem(13) [15:0] $end
   $var wire 16 9 mem(14) [15:0] $end
   $var wire 16 : mem(15) [15:0] $end
   $var wire 16 - mem(2) [15:0] $end
   $var wire 16 . mem(3) [15:0] $end
   $var wire 16 / mem(4) [15:0] $end
   $var wire 16 0 mem(5) [15:0] $end
   $var wire 16 1 mem(6) [15:0] $end
   $var wire 16 2 mem(7) [15:0] $end
   $var wire 16 3 mem(8) [15:0] $end
   $var wire 16 4 mem(9) [15:0] $end
   $var wire 32 % n [31:0] $end
   $var wire  4 & num [3:0] $end
   $var wire  1 ( running $end
   $var wire 32 > start [31:0] $end
   $var wire  1 ) we $end
   $scope module c1 $end
    $var wire  1 < clk $end
    $var wire  1 $ done $end
    $var wire 32 ; dout [31:0] $end
    $var wire  1 # go $end
    $var wire 32 % n [31:0] $end
   $upscope $end
  $upscope $end
 $upscope $end
$enddefinitions $end


#0
0#
0$
b00000000000000000000000000000000 %
b0000 &
b0000 '
0(
0)
b0000000000000000 *
b0000000000000000 +
b0000000000000000 ,
b0000000000000000 -
b0000000000000000 .
b0000000000000000 /
b0000000000000000 0
b0000000000000000 1
b0000000000000000 2
b0000000000000000 3
b0000000000000000 4
b0000000000000000 5
b0000000000000000 6
b0000000000000000 7
b0000000000000000 8
b0000000000000000 9
b0000000000000000 :
b00000000000000000000000000000000 ;
0<
1=
b00000000000000000000000000000111 >
0?
b0000000000000000 @
b0111 A
b00000000000000000000000000010000 B
b00000000000000000000000000000100 C
#10
1#
b00000000000000000000000000000111 %
1(
1<
#20
0<
#30
b00000000000000000000000000000111 ;
1<
#40
0<
0=
#50
0#
1<
b0000000000000001 @
#60
0<
#70
b00000000000000000000000000010110 ;
1<
b0000000000000010 @
#80
0<
#90
b00000000000000000000000000001011 ;
1<
b0000000000000011 @
#100
0<
#110
b00000000000000000000000000100010 ;
1<
b0000000000000100 @
#120
0<
#130
b00000000000000000000000000010001 ;
1<
b0000000000000101 @
#140
0<
#150
b00000000000000000000000000110100 ;
1<
b0000000000000110 @
#160
0<
#170
b00000000000000000000000000011010 ;
1<
b0000000000000111 @
#180
0<
#190
b00000000000000000000000000001101 ;
1<
b0000000000001000 @
#200
0<
#210
b00000000000000000000000000101000 ;
1<
b0000000000001001 @
#220
0<
#230
b00000000000000000000000000010100 ;
1<
b0000000000001010 @
#240
0<
#250
b00000000000000000000000000001010 ;
1<
b0000000000001011 @
#260
0<
#270
b00000000000000000000000000000101 ;
1<
b0000000000001100 @
#280
0<
#290
b00000000000000000000000000010000 ;
1<
b0000000000001101 @
#300
0<
#310
b00000000000000000000000000001000 ;
1<
b0000000000001110 @
#320
0<
#330
b00000000000000000000000000000100 ;
1<
b0000000000001111 @
#340
0<
#350
b00000000000000000000000000000010 ;
1<
b0000000000010000 @
#360
0<
#370
1$
b00000000000000000000000000000001 ;
1<
b0000000000010001 @
#380
0<
#390
1#
b00000000000000000000000000001000 %
b0001 &
1)
b0000000000010001 *
1<
b0000000000000000 @
b0000 A
#400
0<
#410
0#
0$
0)
b0000000000010001 +
b00000000000000000000000000001000 ;
1<
b0000000000000001 @
b0111 A
#420
0<
#430
b00000000000000000000000000000100 ;
1<
b0000000000000010 @
#440
0<
#450
b00000000000000000000000000000010 ;
1<
b0000000000000011 @
#460
0<
#470
1$
b00000000000000000000000000000001 ;
1<
b0000000000000100 @
#480
0<
#490
1#
b00000000000000000000000000001001 %
b0010 &
b0001 '
1)
b0000000000000100 *
1<
b0000000000000000 @
b0001 A
#500
0<
#510
0#
0$
0)
b0000000000000100 ,
b00000000000000000000000000001001 ;
1<
b0000000000000001 @
b0111 A
#520
0<
#530
b00000000000000000000000000011100 ;
1<
b0000000000000010 @
#540
0<
#550
b00000000000000000000000000001110 ;
1<
b0000000000000011 @
#560
0<
#570
b00000000000000000000000000000111 ;
1<
b0000000000000100 @
#580
0<
#590
b00000000000000000000000000010110 ;
1<
b0000000000000101 @
#600
0<
#610
b00000000000000000000000000001011 ;
1<
b0000000000000110 @
#620
0<
#630
b00000000000000000000000000100010 ;
1<
b0000000000000111 @
#640
0<
#650
b00000000000000000000000000010001 ;
1<
b0000000000001000 @
#660
0<
#670
b00000000000000000000000000110100 ;
1<
b0000000000001001 @
#680
0<
#690
b00000000000000000000000000011010 ;
1<
b0000000000001010 @
#700
0<
#710
b00000000000000000000000000001101 ;
1<
b0000000000001011 @
#720
0<
#730
b00000000000000000000000000101000 ;
1<
b0000000000001100 @
#740
0<
#750
b00000000000000000000000000010100 ;
1<
b0000000000001101 @
#760
0<
#770
b00000000000000000000000000001010 ;
1<
b0000000000001110 @
#780
0<
#790
b00000000000000000000000000000101 ;
1<
b0000000000001111 @
#800
0<
#810
b00000000000000000000000000010000 ;
1<
b0000000000010000 @
#820
0<
#830
b00000000000000000000000000001000 ;
1<
b0000000000010001 @
#840
0<
#850
b00000000000000000000000000000100 ;
1<
b0000000000010010 @
#860
0<
#870
b00000000000000000000000000000010 ;
1<
b0000000000010011 @
#880
0<
#890
1$
b00000000000000000000000000000001 ;
1<
b0000000000010100 @
#900
0<
#910
1#
b00000000000000000000000000001010 %
b0011 &
b0010 '
1)
b0000000000010100 *
1<
b0000000000000000 @
b0010 A
#920
0<
#930
0#
0$
0)
b0000000000010100 -
b00000000000000000000000000001010 ;
1<
b0000000000000001 @
b0111 A
#940
0<
#950
b00000000000000000000000000000101 ;
1<
b0000000000000010 @
#960
0<
#970
b00000000000000000000000000010000 ;
1<
b0000000000000011 @
#980
0<
#990
b00000000000000000000000000001000 ;
1<
b0000000000000100 @
#1000
0<
#1010
b00000000000000000000000000000100 ;
1<
b0000000000000101 @
#1020
0<
#1030
b00000000000000000000000000000010 ;
1<
b0000000000000110 @
#1040
0<
#1050
1$
b00000000000000000000000000000001 ;
1<
b0000000000000111 @
#1060
0<
#1070
1#
b00000000000000000000000000001011 %
b0100 &
b0011 '
1)
b0000000000000111 *
1<
b0000000000000000 @
b0011 A
#1080
0<
#1090
0#
0$
0)
b0000000000000111 .
b00000000000000000000000000001011 ;
1<
b0000000000000001 @
b0111 A
#1100
0<
#1110
b00000000000000000000000000100010 ;
1<
b0000000000000010 @
#1120
0<
#1130
b00000000000000000000000000010001 ;
1<
b0000000000000011 @
#1140
0<
#1150
b00000000000000000000000000110100 ;
1<
b0000000000000100 @
#1160
0<
#1170
b00000000000000000000000000011010 ;
1<
b0000000000000101 @
#1180
0<
#1190
b00000000000000000000000000001101 ;
1<
b0000000000000110 @
#1200
0<
#1210
b00000000000000000000000000101000 ;
1<
b0000000000000111 @
#1220
0<
#1230
b00000000000000000000000000010100 ;
1<
b0000000000001000 @
#1240
0<
#1250
b00000000000000000000000000001010 ;
1<
b0000000000001001 @
#1260
0<
#1270
b00000000000000000000000000000101 ;
1<
b0000000000001010 @
#1280
0<
#1290
b00000000000000000000000000010000 ;
1<
b0000000000001011 @
#1300
0<
#1310
b00000000000000000000000000001000 ;
1<
b0000000000001100 @
#1320
0<
#1330
b00000000000000000000000000000100 ;
1<
b0000000000001101 @
#1340
0<
#1350
b00000000000000000000000000000010 ;
1<
b0000000000001110 @
#1360
0<
#1370
1$
b00000000000000000000000000000001 ;
1<
b0000000000001111 @
#1380
0<
#1390
1#
b00000000000000000000000000001100 %
b0101 &
b0100 '
1)
b0000000000001111 *
1<
b0000000000000000 @
b0100 A
#1400
0<
#1410
0#
0$
0)
b0000000000001111 /
b00000000000000000000000000001100 ;
1<
b0000000000000001 @
b0111 A
#1420
0<
#1430
b00000000000000000000000000000110 ;
1<
b0000000000000010 @
#1440
0<
#1450
b00000000000000000000000000000011 ;
1<
b0000000000000011 @
#1460
0<
#1470
b00000000000000000000000000001010 ;
1<
b0000000000000100 @
#1480
0<
#1490
b00000000000000000000000000000101 ;
1<
b0000000000000101 @
#1500
0<
#1510
b00000000000000000000000000010000 ;
1<
b0000000000000110 @
#1520
0<
#1530
b00000000000000000000000000001000 ;
1<
b0000000000000111 @
#1540
0<
#1550
b00000000000000000000000000000100 ;
1<
b0000000000001000 @
#1560
0<
#1570
b00000000000000000000000000000010 ;
1<
b0000000000001001 @
#1580
0<
#1590
1$
b00000000000000000000000000000001 ;
1<
b0000000000001010 @
#1600
0<
#1610
1#
b00000000000000000000000000001101 %
b0110 &
b0101 '
1)
b0000000000001010 *
1<
b0000000000000000 @
b0101 A
#1620
0<
#1630
0#
0$
0)
b0000000000001010 0
b00000000000000000000000000001101 ;
1<
b0000000000000001 @
b0111 A
#1640
0<
#1650
b00000000000000000000000000101000 ;
1<
b0000000000000010 @
#1660
0<
#1670
b00000000000000000000000000010100 ;
1<
b0000000000000011 @
#1680
0<
#1690
b00000000000000000000000000001010 ;
1<
b0000000000000100 @
#1700
0<
#1710
b00000000000000000000000000000101 ;
1<
b0000000000000101 @
#1720
0<
#1730
b00000000000000000000000000010000 ;
1<
b0000000000000110 @
#1740
0<
#1750
b00000000000000000000000000001000 ;
1<
b0000000000000111 @
#1760
0<
#1770
b00000000000000000000000000000100 ;
1<
b0000000000001000 @
#1780
0<
#1790
b00000000000000000000000000000010 ;
1<
b0000000000001001 @
#1800
0<
#1810
1$
b00000000000000000000000000000001 ;
1<
b0000000000001010 @
#1820
0<
#1830
1#
b00000000000000000000000000001110 %
b0111 &
b0110 '
1)
1<
b0000000000000000 @
b0110 A
#1840
0<
#1850
0#
0$
0)
b0000000000001010 1
b00000000000000000000000000001110 ;
1<
b0000000000000001 @
b0111 A
#1860
0<
#1870
b00000000000000000000000000000111 ;
1<
b0000000000000010 @
#1880
0<
#1890
b00000000000000000000000000010110 ;
1<
b0000000000000011 @
#1900
0<
#1910
b00000000000000000000000000001011 ;
1<
b0000000000000100 @
#1920
0<
#1930
b00000000000000000000000000100010 ;
1<
b0000000000000101 @
#1940
0<
#1950
b00000000000000000000000000010001 ;
1<
b0000000000000110 @
#1960
0<
#1970
b00000000000000000000000000110100 ;
1<
b0000000000000111 @
#1980
0<
#1990
b00000000000000000000000000011010 ;
1<
b0000000000001000 @
#2000
0<
#2010
b00000000000000000000000000001101 ;
1<
b0000000000001001 @
#2020
0<
#2030
b00000000000000000000000000101000 ;
1<
b0000000000001010 @
#2040
0<
#2050
b00000000000000000000000000010100 ;
1<
b0000000000001011 @
#2060
0<
#2070
b00000000000000000000000000001010 ;
1<
b0000000000001100 @
#2080
0<
#2090
b00000000000000000000000000000101 ;
1<
b0000000000001101 @
#2100
0<
#2110
b00000000000000000000000000010000 ;
1<
b0000000000001110 @
#2120
0<
#2130
b00000000000000000000000000001000 ;
1<
b0000000000001111 @
#2140
0<
#2150
b00000000000000000000000000000100 ;
1<
b0000000000010000 @
#2160
0<
#2170
b00000000000000000000000000000010 ;
1<
b0000000000010001 @
#2180
0<
#2190
1$
b00000000000000000000000000000001 ;
1<
b0000000000010010 @
#2200
0<
#2210
1#
b00000000000000000000000000001111 %
b1000 &
b0111 '
1)
b0000000000010010 *
1<
b0000000000000000 @
#2220
0<
#2230
0#
0$
0)
b0000000000010010 2
b00000000000000000000000000001111 ;
1<
b0000000000000001 @
#2240
0<
#2250
b00000000000000000000000000101110 ;
1<
b0000000000000010 @
#2260
0<
#2270
b00000000000000000000000000010111 ;
1<
b0000000000000011 @
#2280
0<
#2290
b00000000000000000000000001000110 ;
1<
b0000000000000100 @
#2300
0<
#2310
b00000000000000000000000000100011 ;
1<
b0000000000000101 @
#2320
0<
#2330
b00000000000000000000000001101010 ;
1<
b0000000000000110 @
#2340
0<
#2350
b00000000000000000000000000110101 ;
1<
b0000000000000111 @
#2360
0<
#2370
b00000000000000000000000010100000 ;
1<
b0000000000001000 @
#2380
0<
#2390
b00000000000000000000000001010000 ;
1<
b0000000000001001 @
#2400
0<
#2410
b00000000000000000000000000101000 ;
1<
b0000000000001010 @
#2420
0<
#2430
b00000000000000000000000000010100 ;
1<
b0000000000001011 @
#2440
0<
#2450
b00000000000000000000000000001010 ;
1<
b0000000000001100 @
#2460
0<
#2470
b00000000000000000000000000000101 ;
1<
b0000000000001101 @
#2480
0<
#2490
b00000000000000000000000000010000 ;
1<
b0000000000001110 @
#2500
0<
#2510
b00000000000000000000000000001000 ;
1<
b0000000000001111 @
#2520
0<
#2530
b00000000000000000000000000000100 ;
1<
b0000000000010000 @
#2540
0<
#2550
b00000000000000000000000000000010 ;
1<
b0000000000010001 @
#2560
0<
#2570
1$
b00000000000000000000000000000001 ;
1<
b0000000000010010 @
#2580
0<
#2590
1#
b00000000000000000000000000010000 %
b1001 &
b1000 '
1)
1<
b0000000000000000 @
b1000 A
#2600
0<
#2610
0#
0$
0)
b0000000000010010 3
b00000000000000000000000000010000 ;
1<
b0000000000000001 @
b0111 A
#2620
0<
#2630
b00000000000000000000000000001000 ;
1<
b0000000000000010 @
#2640
0<
#2650
b00000000000000000000000000000100 ;
1<
b0000000000000011 @
#2660
0<
#2670
b00000000000000000000000000000010 ;
1<
b0000000000000100 @
#2680
0<
#2690
1$
b00000000000000000000000000000001 ;
1<
b0000000000000101 @
#2700
0<
#2710
1#
b00000000000000000000000000010001 %
b1010 &
b1001 '
1)
b0000000000000101 *
1<
b0000000000000000 @
b1001 A
#2720
0<
#2730
0#
0$
0)
b0000000000000101 4
b00000000000000000000000000010001 ;
1<
b0000000000000001 @
b0111 A
#2740
0<
#2750
b00000000000000000000000000110100 ;
1<
b0000000000000010 @
#2760
0<
#2770
b00000000000000000000000000011010 ;
1<
b0000000000000011 @
#2780
0<
#2790
b00000000000000000000000000001101 ;
1<
b0000000000000100 @
#2800
0<
#2810
b00000000000000000000000000101000 ;
1<
b0000000000000101 @
#2820
0<
#2830
b00000000000000000000000000010100 ;
1<
b0000000000000110 @
#2840
0<
#2850
b00000000000000000000000000001010 ;
1<
b0000000000000111 @
#2860
0<
#2870
b00000000000000000000000000000101 ;
1<
b0000000000001000 @
#2880
0<
#2890
b00000000000000000000000000010000 ;
1<
b0000000000001001 @
#2900
0<
#2910
b00000000000000000000000000001000 ;
1<
b0000000000001010 @
#2920
0<
#2930
b00000000000000000000000000000100 ;
1<
b0000000000001011 @
#2940
0<
#2950
b00000000000000000000000000000010 ;
1<
b0000000000001100 @
#2960
0<
#2970
1$
b00000000000000000000000000000001 ;
1<
b0000000000001101 @
#2980
0<
#2990
1#
b00000000000000000000000000010010 %
b1011 &
b1010 '
1)
b0000000000001101 *
1<
b0000000000000000 @
b1010 A
#3000
0<
#3010
0#
0$
0)
b0000000000001101 5
b00000000000000000000000000010010 ;
1<
b0000000000000001 @
b0111 A
#3020
0<
#3030
b00000000000000000000000000001001 ;
1<
b0000000000000010 @
#3040
0<
#3050
b00000000000000000000000000011100 ;
1<
b0000000000000011 @
#3060
0<
#3070
b00000000000000000000000000001110 ;
1<
b0000000000000100 @
#3080
0<
#3090
b00000000000000000000000000000111 ;
1<
b0000000000000101 @
#3100
0<
#3110
b00000000000000000000000000010110 ;
1<
b0000000000000110 @
#3120
0<
#3130
b00000000000000000000000000001011 ;
1<
b0000000000000111 @
#3140
0<
#3150
b00000000000000000000000000100010 ;
1<
b0000000000001000 @
#3160
0<
#3170
b00000000000000000000000000010001 ;
1<
b0000000000001001 @
#3180
0<
#3190
b00000000000000000000000000110100 ;
1<
b0000000000001010 @
#3200
0<
#3210
b00000000000000000000000000011010 ;
1<
b0000000000001011 @
#3220
0<
#3230
b00000000000000000000000000001101 ;
1<
b0000000000001100 @
#3240
0<
#3250
b00000000000000000000000000101000 ;
1<
b0000000000001101 @
#3260
0<
#3270
b00000000000000000000000000010100 ;
1<
b0000000000001110 @
#3280
0<
#3290
b00000000000000000000000000001010 ;
1<
b0000000000001111 @
#3300
0<
#3310
b00000000000000000000000000000101 ;
1<
b0000000000010000 @
#3320
0<
#3330
b00000000000000000000000000010000 ;
1<
b0000000000010001 @
#3340
0<
#3350
b00000000000000000000000000001000 ;
1<
b0000000000010010 @
#3360
0<
#3370
b00000000000000000000000000000100 ;
1<
b0000000000010011 @
#3380
0<
#3390
b00000000000000000000000000000010 ;
1<
b0000000000010100 @
#3400
0<
#3410
1$
b00000000000000000000000000000001 ;
1<
b0000000000010101 @
#3420
0<
#3430
1#
b00000000000000000000000000010011 %
b1100 &
b1011 '
1)
b0000000000010101 *
1<
b0000000000000000 @
b1011 A
#3440
0<
#3450
0#
0$
0)
b0000000000010101 6
b00000000000000000000000000010011 ;
1<
b0000000000000001 @
b0111 A
#3460
0<
#3470
b00000000000000000000000000111010 ;
1<
b0000000000000010 @
#3480
0<
#3490
b00000000000000000000000000011101 ;
1<
b0000000000000011 @
#3500
0<
#3510
b00000000000000000000000001011000 ;
1<
b0000000000000100 @
#3520
0<
#3530
b00000000000000000000000000101100 ;
1<
b0000000000000101 @
#3540
0<
#3550
b00000000000000000000000000010110 ;
1<
b0000000000000110 @
#3560
0<
#3570
b00000000000000000000000000001011 ;
1<
b0000000000000111 @
#3580
0<
#3590
b00000000000000000000000000100010 ;
1<
b0000000000001000 @
#3600
0<
#3610
b00000000000000000000000000010001 ;
1<
b0000000000001001 @
#3620
0<
#3630
b00000000000000000000000000110100 ;
1<
b0000000000001010 @
#3640
0<
#3650
b00000000000000000000000000011010 ;
1<
b0000000000001011 @
#3660
0<
#3670
b00000000000000000000000000001101 ;
1<
b0000000000001100 @
#3680
0<
#3690
b00000000000000000000000000101000 ;
1<
b0000000000001101 @
#3700
0<
#3710
b00000000000000000000000000010100 ;
1<
b0000000000001110 @
#3720
0<
#3730
b00000000000000000000000000001010 ;
1<
b0000000000001111 @
#3740
0<
#3750
b00000000000000000000000000000101 ;
1<
b0000000000010000 @
#3760
0<
#3770
b00000000000000000000000000010000 ;
1<
b0000000000010001 @
#3780
0<
#3790
b00000000000000000000000000001000 ;
1<
b0000000000010010 @
#3800
0<
#3810
b00000000000000000000000000000100 ;
1<
b0000000000010011 @
#3820
0<
#3830
b00000000000000000000000000000010 ;
1<
b0000000000010100 @
#3840
0<
#3850
1$
b00000000000000000000000000000001 ;
1<
b0000000000010101 @
#3860
0<
#3870
1#
b00000000000000000000000000010100 %
b1101 &
b1100 '
1)
1<
b0000000000000000 @
b1100 A
#3880
0<
#3890
0#
0$
0)
b0000000000010101 7
b00000000000000000000000000010100 ;
1<
b0000000000000001 @
b0111 A
#3900
0<
#3910
b00000000000000000000000000001010 ;
1<
b0000000000000010 @
#3920
0<
#3930
b00000000000000000000000000000101 ;
1<
b0000000000000011 @
#3940
0<
#3950
b00000000000000000000000000010000 ;
1<
b0000000000000100 @
#3960
0<
#3970
b00000000000000000000000000001000 ;
1<
b0000000000000101 @
#3980
0<
#3990
b00000000000000000000000000000100 ;
1<
b0000000000000110 @
#4000
0<
#4010
b00000000000000000000000000000010 ;
1<
b0000000000000111 @
#4020
0<
#4030
1$
b00000000000000000000000000000001 ;
1<
b0000000000001000 @
#4040
0<
#4050
1#
b00000000000000000000000000010101 %
b1110 &
b1101 '
1)
b0000000000001000 *
1<
b0000000000000000 @
b1101 A
#4060
0<
#4070
0#
0$
0)
b0000000000001000 8
b00000000000000000000000000010101 ;
1<
b0000000000000001 @
b0111 A
#4080
0<
#4090
b00000000000000000000000001000000 ;
1<
b0000000000000010 @
#4100
0<
#4110
b00000000000000000000000000100000 ;
1<
b0000000000000011 @
#4120
0<
#4130
b00000000000000000000000000010000 ;
1<
b0000000000000100 @
#4140
0<
#4150
b00000000000000000000000000001000 ;
1<
b0000000000000101 @
#4160
0<
#4170
b00000000000000000000000000000100 ;
1<
b0000000000000110 @
#4180
0<
#4190
b00000000000000000000000000000010 ;
1<
b0000000000000111 @
#4200
0<
#4210
1$
b00000000000000000000000000000001 ;
1<
b0000000000001000 @
#4220
0<
#4230
1#
b00000000000000000000000000010110 %
b1111 &
b1110 '
1)
1<
b0000000000000000 @
b1110 A
#4240
0<
#4250
0#
0$
0)
b0000000000001000 9
b00000000000000000000000000010110 ;
1<
b0000000000000001 @
b0111 A
#4260
0<
#4270
b00000000000000000000000000001011 ;
1<
b0000000000000010 @
#4280
0<
#4290
b00000000000000000000000000100010 ;
1<
b0000000000000011 @
#4300
0<
#4310
b00000000000000000000000000010001 ;
1<
b0000000000000100 @
#4320
0<
#4330
b00000000000000000000000000110100 ;
1<
b0000000000000101 @
#4340
0<
#4350
b00000000000000000000000000011010 ;
1<
b0000000000000110 @
#4360
0<
#4370
b00000000000000000000000000001101 ;
1<
b0000000000000111 @
#4380
0<
#4390
b00000000000000000000000000101000 ;
1<
b0000000000001000 @
#4400
0<
#4410
b00000000000000000000000000010100 ;
1<
b0000000000001001 @
#4420
0<
#4430
b00000000000000000000000000001010 ;
1<
b0000000000001010 @
#4440
0<
#4450
b00000000000000000000000000000101 ;
1<
b0000000000001011 @
#4460
0<
#4470
b00000000000000000000000000010000 ;
1<
b0000000000001100 @
#4480
0<
#4490
b00000000000000000000000000001000 ;
1<
b0000000000001101 @
#4500
0<
#4510
b00000000000000000000000000000100 ;
1<
b0000000000001110 @
#4520
0<
#4530
b00000000000000000000000000000010 ;
1<
b0000000000001111 @
#4540
0<
#4550
1$
b00000000000000000000000000000001 ;
1<
b0000000000010000 @
#4560
0<
#4570
0(
1<
1?
b0000000000010010 @
#4580
0<
b00000000000000000000000000000000 >
b0000 A
#4590
1<
0?
b0000000000010001 @
#4600
0<
b00000000000000000000000000000001 >
b0001 A
#4610
1<
b0000000000000100 @
#4620
0<
b00000000000000000000000000000010 >
b0010 A
#4630
1<
b0000000000010100 @
#4640
0<
b00000000000000000000000000000011 >
b0011 A
#4650
1<
b0000000000000111 @
#4660
0<
b00000000000000000000000000000100 >
b0100 A
#4670
1<
b0000000000001111 @
#4680
0<
b00000000000000000000000000000101 >
b0101 A
#4690
1<
b0000000000001010 @
#4700
0<
b00000000000000000000000000000110 >
b0110 A
#4710
1<
#4720
0<
b00000000000000000000000000000111 >
b0111 A
#4730
1<
b0000000000010010 @
#4740
0<
b00000000000000000000000000001000 >
b1000 A
#4750
1<
#4760
0<
b00000000000000000000000000001001 >
b1001 A
#4770
1<
b0000000000000101 @
#4780
0<
b00000000000000000000000000001010 >
b1010 A
#4790
1<
b0000000000001101 @
#4800
0<
b00000000000000000000000000001011 >
b1011 A
#4810
1<
b0000000000010101 @
#4820
0<
b00000000000000000000000000001100 >
b1100 A
#4830
1<
#4840
0<
b00000000000000000000000000001101 >
b1101 A
#4850
1<
b0000000000001000 @
#4860
0<
b00000000000000000000000000001110 >
b1110 A
#4870
1<
#4880
0<
b00000000000000000000000000001111 >
b1111 A
#4890
1<
b0000000000000000 @
